mysqlpool_wrapper/__init__.py
mysqlpool_wrapper/_version.py
mysqlpool_wrapper/mysqlpool.py
mysqlpool_wrapper-0.2.2.dist-info/LICENSE.txt
mysqlpool_wrapper-0.2.2.dist-info/METADATA
mysqlpool_wrapper-0.2.2.dist-info/WHEEL
mysqlpool_wrapper-0.2.2.dist-info/top_level.txt
mysqlpool_wrapper-0.2.2.dist-info/RECORD
