Metadata-Version: 2.1
Name: mysqlpool-wrapper
Version: 0.2.2
Summary: Library which is used as MySQL pool wrapper.
Home-page: https://github.com/mmedek/mysqlpool-wrapper
Author: Michal Medek
Author-email: mmedek94@gmail.com
License: UNKNOWN
Keywords: mysql,mysql pool
Platform: any
License-File: LICENSE.txt
Requires-Dist: mysql-connector-python (>=8.0.23)
Requires-Dist: mysqlclient (>=2.0.3)
Requires-Dist: sqlalchemy (>=1.3.20)
